{
  "id": 161,
  "name": "Two Dots 70",
  "creator": "Enno",
  "description": "",
  "folder": "Two Dots",
  "numColumns": 8,
  "numRows": 6,
  "grid": [
    "  ....  ",
    ". .... .",
    ". .... .",
    ". .LR. .",
    ". .  . .",
    "...  ..."
  ],
  "ice": [
    "........",
    "3......3",
    "3......3",
    "3......3",
    "3.3..3.3",
    "333..333"
  ],
  "items": [
    "..????..",
    "F.????.F",
    "F.????.F",
    "F.?..?.F",
    "F.?..?.F",
    "F??..??F"
  ],
  "teleporters": [  ],
  "doors": [  ],
  "conveyors": [  ],
  "lazySusans": [  ],
  "dots": [  ],
  "animals": [  ],
  "knights": [  ],
  "clocks": [  ],
  "lasers": [  ],
  "mirrors": [  ],
  "rockets": [  ],
  "generator": {
    "generateLetters": false,
    "seed": -1,
    "fireGrowthRate": 1,
    "maxAnchors": 3,
    "initialDotsOnly": true,
    "animalStrength": 10,
    "knightStrength": 3,
    "clockStrength": 10,
    "animalType": "Default",
    "freq": [
      [33.3,"dot",2],
      [33.4,"dot",3],
      [33.3,"dot",4]
    ]
  },
  "goals": {
    "dots": {
      "2": 75,
      "4": 75
    },
    "maxMoves": 17,
    "ice": -1
  },
  "lastModified": "1446250258542"
}